poetry_template/__init__.py
poetry_template1-0.1.0.dist-info/METADATA
poetry_template1-0.1.0.dist-info/WHEEL
poetry_template1-0.1.0.dist-info/RECORD
