Metadata-Version: 2.1
Name: poetry-template1
Version: 0.1.0
Summary: 
Author: lgf4591
Author-email: lgf4591@outlook.com
Requires-Python: >=3.11,<4.0
Classifier: Programming Language :: Python :: 3
Classifier: Programming Language :: Python :: 3.11
Classifier: Programming Language :: Python :: 3.12
Requires-Dist: python-dotenv (>=1.0.0,<2.0.0)
